biobb_pdb_tools/__init__.py
biobb_pdb_tools/py.typed
biobb_pdb_tools/pdb_tools/__init__.py
biobb_pdb_tools/pdb_tools/biobb_pdb_chain.py
biobb_pdb_tools/pdb_tools/biobb_pdb_chainxseg.py
biobb_pdb_tools/pdb_tools/biobb_pdb_delhetatm.py
biobb_pdb_tools/pdb_tools/biobb_pdb_fetch.py
biobb_pdb_tools/pdb_tools/biobb_pdb_fixinsert.py
biobb_pdb_tools/pdb_tools/biobb_pdb_keepcoord.py
biobb_pdb_tools/pdb_tools/biobb_pdb_merge.py
biobb_pdb_tools/pdb_tools/biobb_pdb_mkensemble.py
biobb_pdb_tools/pdb_tools/biobb_pdb_reres.py
biobb_pdb_tools/pdb_tools/biobb_pdb_seg.py
biobb_pdb_tools/pdb_tools/biobb_pdb_selaltloc.py
biobb_pdb_tools/pdb_tools/biobb_pdb_selchain.py
biobb_pdb_tools/pdb_tools/biobb_pdb_selres.py
biobb_pdb_tools/pdb_tools/biobb_pdb_splitmodel.py
biobb_pdb_tools/pdb_tools/biobb_pdb_splitseg.py
biobb_pdb_tools/pdb_tools/biobb_pdb_tidy.py
biobb_pdb_tools/pdb_tools/biobb_pdb_tofasta.py
biobb_pdb_tools/pdb_tools/biobb_pdb_uniqname.py
biobb_pdb_tools/test/__init__.py
biobb_pdb_tools-5.2.0.dist-info/licenses/LICENSE
biobb_pdb_tools-5.2.0.dist-info/METADATA
biobb_pdb_tools-5.2.0.dist-info/WHEEL
biobb_pdb_tools-5.2.0.dist-info/entry_points.txt
biobb_pdb_tools-5.2.0.dist-info/top_level.txt
biobb_pdb_tools-5.2.0.dist-info/RECORD
